semantio/__init__.py
semantio/agent.py
semantio/memory.py
semantio/models.py
semantio/rag.py
semantio/api/__init__.py
semantio/api/api_generator.py
semantio/api/fastapi_app.py
semantio/cli/__init__.py
semantio/cli/main.py
semantio/knowledge_base/__init__.py
semantio/knowledge_base/document_loader.py
semantio/knowledge_base/retriever.py
semantio/knowledge_base/vector_store.py
semantio/llm/__init__.py
semantio/llm/anthropic.py
semantio/llm/base_llm.py
semantio/llm/deepseek.py
semantio/llm/gemini.py
semantio/llm/groq.py
semantio/llm/mistral.py
semantio/llm/openai.py
semantio/storage/__init__.py
semantio/storage/base_storage.py
semantio/storage/cloud_storage.py
semantio/storage/in_memory_storage.py
semantio/storage/local_storage.py
semantio/tools/__init__.py
semantio/tools/base_tool.py
semantio/tools/crypto.py
semantio/tools/duckduckgo.py
semantio/tools/stocks.py
semantio/tools/web_browser.py
semantio/utils/__init__.py
semantio/utils/config.py
semantio/utils/date_utils.py
semantio/utils/file_utils.py
semantio/utils/logger.py
semantio/utils/validation_utils.py
semantio-0.0.8.dist-info/LICENSE
semantio-0.0.8.dist-info/METADATA
semantio-0.0.8.dist-info/WHEEL
semantio-0.0.8.dist-info/entry_points.txt
semantio-0.0.8.dist-info/top_level.txt
semantio-0.0.8.dist-info/RECORD
