Metadata-Version: 2.1
Name: semantio
Version: 0.0.8
Summary: A powerful SDK for building AI agents
Home-page: https://github.com/Syenah/semantio
Author: Rakesh
Author-email: rakeshsahoo689@gmail.com
License: UNKNOWN
Platform: UNKNOWN
Classifier: Development Status :: 3 - Alpha
Classifier: Intended Audience :: Developers
Classifier: License :: OSI Approved :: MIT License
Classifier: Programming Language :: Python :: 3.8
Classifier: Programming Language :: Python :: 3.9
Classifier: Programming Language :: Python :: 3.10
Requires-Python: >=3.8
License-File: LICENSE
Requires-Dist: openai
Requires-Dist: anthropic
Requires-Dist: groq
Requires-Dist: google-genai
Requires-Dist: mistralai
Requires-Dist: faiss-cpu
Requires-Dist: pydantic
Requires-Dist: requests
Requires-Dist: playwright
Requires-Dist: fastapi
Requires-Dist: uvicorn
Requires-Dist: pillow
Requires-Dist: slowapi
Requires-Dist: sentence-transformers
Requires-Dist: fuzzywuzzy
Requires-Dist: duckduckgo-search
Requires-Dist: yfinance
Requires-Dist: beautifulsoup4
Requires-Dist: webdriver-manager
Requires-Dist: validators
Requires-Dist: PyPDF2
Requires-Dist: youtube-transcript-api
Requires-Dist: pandas
